emvoice/__init__.py
emvoice/energy.py
emvoice/formants.py
emvoice/frames.py
emvoice/pitch.py
emvoice/signal.py
emvoice/spectral.py
emvoice-0.1.1.dist-info/LICENSE
emvoice-0.1.1.dist-info/METADATA
emvoice-0.1.1.dist-info/NOTICE
emvoice-0.1.1.dist-info/WHEEL
emvoice-0.1.1.dist-info/top_level.txt
emvoice-0.1.1.dist-info/RECORD
